inject/__init__.py
inject/__init__.pyi
inject/_version.py
inject/py.typed
inject2-5.2.1.dist-info/METADATA
inject2-5.2.1.dist-info/WHEEL
inject2-5.2.1.dist-info/licenses/LICENSE
inject2-5.2.1.dist-info/RECORD
