Metadata-Version: 2.1
Name: inject2
Version: 5.2.1
Summary: Python dependency injection framework.
Project-URL: Homepage, https://github.com/fzyukio/python-inject
Author-email: Ivan Korobkov <ivan.korobkov@gmail.com>
Maintainer-email: Ivan Korobkov <ivan.korobkov@gmail.com>
License-Expression: Apache-2.0
License-File: LICENSE
Classifier: Development Status :: 5 - Production/Stable
Classifier: Intended Audience :: Developers
Classifier: License :: OSI Approved :: Apache Software License
Classifier: Operating System :: OS Independent
Classifier: Programming Language :: Python
Classifier: Programming Language :: Python :: 3.9
Classifier: Programming Language :: Python :: 3.10
Classifier: Programming Language :: Python :: 3.11
Classifier: Topic :: Software Development :: Libraries :: Python Modules
